report_volo/__init__.py
report_volo/report.py
report_volo-0.2.0.dist-info/METADATA
report_volo-0.2.0.dist-info/WHEEL
report_volo-0.2.0.dist-info/RECORD
