Metadata-Version: 2.3
Name: report_volo
Version: 0.2.0
Summary: A report generation package for results of Monaco 2018 Racing
Project-URL: Homepage, https://git.foxminded.ua/volodymyr-perehuda-nyc/task-6-report-of-monaco-2018-racing
Project-URL: Issues, https://git.foxminded.ua/volodymyr-perehuda-nyc/task-6-report-of-monaco-2018-racing/issues
Author-email: Volodymyr Perehuda <author@example.com>
Keywords: report volo,volo report,your
Classifier: License :: OSI Approved :: MIT License
Classifier: Operating System :: OS Independent
Classifier: Programming Language :: Python :: 3.12
Requires-Python: >=3.12.3
